Metadata-Version: 1.1
Name: pyitachip2ir
Version: 0.0.4
Summary: A library for sending IR commands to an ITach IP2IR gateway
Home-page: https://bitbucket.com/pallindo/itachip2ir
Author: Alan Fischer
Author-email: alan@lightningtoads.com
License: MIT
Keywords: itach ip2ir homeautomation
Platform: UNKNOWN
Classifier: Development Status :: 3 - Alpha
Classifier: Intended Audience :: Developers
Classifier: Topic :: Home Automation
Classifier: License :: OSI Approved :: MIT License
Classifier: Programming Language :: Python :: 2
Classifier: Programming Language :: Python :: 2.6
Classifier: Programming Language :: Python :: 2.7
Classifier: Programming Language :: Python :: 3
Classifier: Programming Language :: Python :: 3.3
Classifier: Programming Language :: Python :: 3.4
Classifier: Programming Language :: Python :: 3.5
